Metadata-Version: 1.1
Name: rubix-cube
Version: 0.1.8
Summary: Python Rubix Cube GUI package
Home-page: https://github.com/dgrethlein/RubixCube
Author: David Grethlein
Author-email: 12dgrethlein@gmail.com
License: MIT
Download-URL: https://github.com/dgrethlein/RubixCube/archive/v0.1.8.tar.gz
Keywords: Python,GUI,Rubix,A*
Platform: UNKNOWN
Classifier: Development Status :: 3 - Alpha
Classifier: Intended Audience :: Developers
Classifier: Intended Audience :: End Users/Desktop
Classifier: Topic :: Games/Entertainment :: Arcade
Classifier: License :: OSI Approved :: MIT License
Classifier: Programming Language :: Python :: 3.7
